xmlsafemod.py
xml_safe_mod-0.1.0.dist-info/METADATA
xml_safe_mod-0.1.0.dist-info/WHEEL
xml_safe_mod-0.1.0.dist-info/entry_points.txt
xml_safe_mod-0.1.0.dist-info/licenses/LICENSE
xml_safe_mod-0.1.0.dist-info/RECORD
