Metadata-Version: 2.1
Name: xml-safe-mod
Version: 0.1.0
Summary: A utility for safely making updates to XML configuration files.
Project-URL: Documentation, https://github.com/kgaughan/xml-safe-mod
Project-URL: Issues, https://github.com/kgaughan/xml-safe-mod/issues
Project-URL: Source, https://github.com/kgaughan/xml-safe-mod
Author-email: Keith Gaughan <k@stereochro.me>
License-Expression: MIT
License-File: LICENSE
Classifier: Development Status :: 4 - Beta
Classifier: Programming Language :: Python
Classifier: Programming Language :: Python :: 3.7
Classifier: Programming Language :: Python :: 3.8
Classifier: Programming Language :: Python :: 3.9
Classifier: Programming Language :: Python :: 3.10
Classifier: Programming Language :: Python :: 3.11
Classifier: Programming Language :: Python :: Implementation :: CPython
Classifier: Programming Language :: Python :: Implementation :: PyPy
Requires-Python: >=3.7
